torch_phase_shift/__init__.py
torch_phase_shift/dft_utils.py
torch_phase_shift/fftfreq_grids.py
torch_phase_shift/phase_shift_dft.py
torch_phase_shift/phase_shift_grids.py
torch_phase_shift/phase_shift_image.py
torch_phase_shift-0.0.2.dist-info/METADATA
torch_phase_shift-0.0.2.dist-info/WHEEL
torch_phase_shift-0.0.2.dist-info/licenses/LICENSE
torch_phase_shift-0.0.2.dist-info/RECORD
