Metadata-Version: 2.3
Name: torch-phase-shift
Version: 0.0.2
Summary: Translate images by phase shifting Fourier transforms in PyTorch
Project-URL: homepage, https://github.com/alisterburt/torch-phase-shift
Project-URL: repository, https://github.com/alisterburt/torch-phase-shift
Author-email: Alister Burt <alisterburt@gmail.com>
License: BSD-3-Clause
License-File: LICENSE
Classifier: Development Status :: 3 - Alpha
Classifier: License :: OSI Approved :: BSD License
Classifier: Programming Language :: Python :: 3
Classifier: Programming Language :: Python :: 3.9
Classifier: Programming Language :: Python :: 3.10
Classifier: Programming Language :: Python :: 3.11
Classifier: Programming Language :: Python :: 3.12
Classifier: Typing :: Typed
Requires-Python: >=3.9
Requires-Dist: einops
Requires-Dist: numpy
Requires-Dist: torch
Provides-Extra: dev
Requires-Dist: ipython; extra == 'dev'
Requires-Dist: mypy; extra == 'dev'
Requires-Dist: pdbpp; extra == 'dev'
Requires-Dist: pre-commit; extra == 'dev'
Requires-Dist: rich; extra == 'dev'
Requires-Dist: ruff; extra == 'dev'
Provides-Extra: test
Requires-Dist: pytest; extra == 'test'
Requires-Dist: pytest-cov; extra == 'test'
